{
  "groupName" : "21ВЕБ-3",
  "days" : [ {
    "day" : "Monday",
    "lessons" : [ {
      "number" : 0,
      "name" : null,
      "teacher" : null,
      "place" : null
    }, {
      "number" : 1,
      "name" : null,
      "teacher" : null,
      "place" : null
    }, {
      "number" : 2,
      "name" : null,
      "teacher" : null,
      "place" : null
    }, {
      "number" : 3,
      "name" : null,
      "teacher" : null,
      "place" : null
    }, {
      "number" : 4,
      "name" : "Математика",
      "teacher" : "Гущина М. В.",
      "place" : "319"
    }, {
      "number" : 5,
      "name" : "Физ-Ра",
      "teacher" : null,
      "place" : null
    }, {
      "number" : 6,
      "name" : "История (1 Группа)",
      "teacher" : "Акьюлов А. С.",
      "place" : "319"
    }, {
      "number" : 6,
      "name" : "Лит-Ра (2 Группа)",
      "teacher" : "Бокарева С. Ф.",
      "place" : "319"
    } ]
  }, {
    "day" : "Tuesday",
    "lessons" : [ {
      "number" : 0,
      "name" : null,
      "teacher" : null,
      "place" : null
    }, {
      "number" : 1,
      "name" : "Математика",
      "teacher" : "Гущина М. В.",
      "place" : "214"
    }, {
      "number" : 2,
      "name" : "Баш. Яз.",
      "teacher" : "Хисамутдинова Р. М.",
      "place" : "214"
    }, {
      "number" : 3,
      "name" : "Физика",
      "teacher" : "Нагаев Р. А.",
      "place" : "214"
    }, {
      "number" : 4,
      "name" : "География",
      "teacher" : null,
      "place" : "214"
    }, {
      "number" : 5,
      "name" : null,
      "teacher" : null,
      "place" : null
    }, {
      "number" : 6,
      "name" : null,
      "teacher" : null,
      "place" : null
    } ]
  }, {
    "day" : "Wednesday",
    "lessons" : [ {
      "number" : 0,
      "name" : null,
      "teacher" : null,
      "place" : null
    }, {
      "number" : 1,
      "name" : null,
      "teacher" : null,
      "place" : null
    }, {
      "number" : 2,
      "name" : "Химия",
      "teacher" : "Акбарова Р. Х.",
      "place" : "309"
    }, {
      "number" : 3,
      "name" : "Русский",
      "teacher" : "Бокарева С. Ф.",
      "place" : "309"
    }, {
      "number" : 4,
      "name" : null,
      "teacher" : null,
      "place" : null
    }, {
      "number" : 5,
      "name" : null,
      "teacher" : null,
      "place" : null
    }, {
      "number" : 6,
      "name" : null,
      "teacher" : null,
      "place" : null
    } ]
  }, {
    "day" : "Thursday",
    "lessons" : [ {
      "number" : 0,
      "name" : "Ин. Яз. (1 Группа)",
      "teacher" : "Валеева З. М.",
      "place" : "314"
    }, {
      "number" : 0,
      "name" : "Физ-Ра (2 Группа)",
      "teacher" : null,
      "place" : null
    }, {
      "number" : 1,
      "name" : "Математика",
      "teacher" : "Гущина М. В.",
      "place" : "314"
    }, {
      "number" : 2,
      "name" : "Информатика",
      "teacher" : null,
      "place" : "314"
    }, {
      "number" : 3,
      "name" : null,
      "teacher" : null,
      "place" : null
    }, {
      "number" : 4,
      "name" : null,
      "teacher" : null,
      "place" : null
    }, {
      "number" : 5,
      "name" : null,
      "teacher" : null,
      "place" : null
    }, {
      "number" : 6,
      "name" : null,
      "teacher" : null,
      "place" : null
    } ]
  }, {
    "day" : "Friday",
    "lessons" : [ {
      "number" : 0,
      "name" : null,
      "teacher" : null,
      "place" : null
    }, {
      "number" : 1,
      "name" : null,
      "teacher" : null,
      "place" : null
    }, {
      "number" : 2,
      "name" : null,
      "teacher" : null,
      "place" : null
    }, {
      "number" : 3,
      "name" : null,
      "teacher" : null,
      "place" : null
    }, {
      "number" : 4,
      "name" : "Ин. Яз.",
      "teacher" : "Валеева З. М.",
      "place" : "315"
    }, {
      "number" : 5,
      "name" : "Физика",
      "teacher" : "Нагаев Р. А.",
      "place" : "315"
    }, {
      "number" : 6,
      "name" : "Общество",
      "teacher" : "Салихов Г. Г.",
      "place" : "315"
    } ]
  }, {
    "day" : "Saturday",
    "lessons" : [ {
      "number" : 0,
      "name" : null,
      "teacher" : null,
      "place" : null
    }, {
      "number" : 1,
      "name" : null,
      "teacher" : null,
      "place" : null
    }, {
      "number" : 2,
      "name" : "Физ-Ра",
      "teacher" : null,
      "place" : null
    }, {
      "number" : 3,
      "name" : "История",
      "teacher" : "Акьюлов А. С.",
      "place" : "214"
    }, {
      "number" : 4,
      "name" : "ОБЖ",
      "teacher" : "Кобелева С. В.",
      "place" : "214"
    }, {
      "number" : 5,
      "name" : null,
      "teacher" : null,
      "place" : null
    }, {
      "number" : 6,
      "name" : null,
      "teacher" : null,
      "place" : null
    } ]
  }, {
    "day" : "Sunday",
    "lessons" : [ {
      "number" : 0,
      "name" : null,
      "teacher" : null,
      "place" : null
    }, {
      "number" : 1,
      "name" : null,
      "teacher" : null,
      "place" : null
    }, {
      "number" : 2,
      "name" : null,
      "teacher" : null,
      "place" : null
    }, {
      "number" : 3,
      "name" : null,
      "teacher" : null,
      "place" : null
    }, {
      "number" : 4,
      "name" : null,
      "teacher" : null,
      "place" : null
    }, {
      "number" : 5,
      "name" : null,
      "teacher" : null,
      "place" : null
    }, {
      "number" : 6,
      "name" : null,
      "teacher" : null,
      "place" : null
    } ]
  } ]
}